unique_session/__init__.py
unique_session/models.py
unique_session/views.py
unique_session/backends/__init__.py
unique_session/backends/session_backend.py
django_unique_session-1.0.dist-info/AUTHORS
django_unique_session-1.0.dist-info/LICENSE
django_unique_session-1.0.dist-info/METADATA
django_unique_session-1.0.dist-info/WHEEL
django_unique_session-1.0.dist-info/top_level.txt
django_unique_session-1.0.dist-info/zip-safe
django_unique_session-1.0.dist-info/RECORD
