Metadata-Version: 2.1
Name: django-unique-session
Version: 1.0
Summary: Unique session handler for Django
Author: Gaël Le Mignot
Author-email: gael@pilotsystems.net
License: GPL v3
Platform: OS Independent
Classifier: Environment :: Web Environment
Classifier: Framework :: Django
Classifier: Programming Language :: Python
License-File: LICENSE
License-File: AUTHORS
